GridMapDecompose/__init__.py
GridMapDecompose/graph_handling.py
GridMapDecompose/map_handling.py
GridMapDecompose/segment_handling.py
GridMapDecompose/slice_handling.py
GridMapDecompose-0.1.7.dist-info/LICENSE
GridMapDecompose-0.1.7.dist-info/METADATA
GridMapDecompose-0.1.7.dist-info/WHEEL
GridMapDecompose-0.1.7.dist-info/top_level.txt
GridMapDecompose-0.1.7.dist-info/RECORD
