Metadata-Version: 2.1
Name: GridMapDecompose
Version: 0.1.7
Summary: Simple pacakge for grid map decomposition
Home-page: UNKNOWN
Author: Tomasz Kucner
Author-email: tomasz.kucner@oru.se
License: UNKNOWN
Project-URL: Author, https://mro.oru.se/people/tomasz-kucner/
Project-URL: Source, https://github.com/tkucner/GridMapDecompose
Project-URL: Tracker, https://github.com/tkucner/GridMapDecompose/issues
Platform: UNKNOWN
Classifier: Programming Language :: Python :: 3
Classifier: License :: OSI Approved :: GNU General Public License v3 (GPLv3)
Classifier: Operating System :: OS Independent
Requires-Dist: numpy (>=1.16.4)
Requires-Dist: scipy (>=1.2.1)
Requires-Dist: scikit-image (>=0.15.0)
Requires-Dist: networkx (>=2.3)
